badiello/__init__.py
prova_badiello-3.1.0.dist-info/METADATA
prova_badiello-3.1.0.dist-info/WHEEL
prova_badiello-3.1.0.dist-info/top_level.txt
prova_badiello-3.1.0.dist-info/RECORD
