Metadata-Version: 2.1
Name: prova_badiello
Version: 3.1.0
Summary: A simple package that prints Hello World
Author: Il tuo nome
Author-email: marco.baddy04@gmial.com
Classifier: Programming Language :: Python :: 3
Classifier: License :: OSI Approved :: MIT License
Classifier: Operating System :: OS Independent
Requires-Python: >=3.6
